{"version":1,"resource":"file:///home/fabian/Documents/Univesity/CMP4266_Computer_Programming/Hospital-Management-System/Admin.py","entries":[{"id":"mlo6.py","timestamp":1732288005896},{"id":"ScfC.py","timestamp":1732288433485},{"id":"8p4q.py","timestamp":1732289635133},{"id":"4uJK.py","timestamp":1732291664040},{"id":"Ndu9.py","timestamp":1732291778859},{"id":"CvXk.py","timestamp":1732292242488},{"id":"A2CG.py","timestamp":1732292281056},{"id":"GzC7.py","timestamp":1732292316113},{"id":"dz2I.py","timestamp":1732292347170},{"id":"iJVK.py","timestamp":1732292364750},{"id":"1siw.py","timestamp":1732292860277},{"id":"c8bj.py","timestamp":1732293056665},{"id":"CFIh.py","timestamp":1732293623121},{"id":"WLqq.py","timestamp":1732293645533},{"id":"GEHi.py","timestamp":1732293939240},{"id":"qIP9.py","timestamp":1732294507361},{"id":"wsMg.py","timestamp":1732294695278},{"id":"tg9R.py","timestamp":1732295050256},{"id":"NJdy.py","timestamp":1732295114091},{"id":"D8nm.py","timestamp":1732295166205},{"id":"RZdg.py","timestamp":1732295469314},{"id":"bqAx.py","timestamp":1732295792122},{"id":"PcHM.py","source":"undoRedo.source","timestamp":1732295955157},{"id":"dKM1.py","timestamp":1732296237299},{"id":"Zla5.py","source":"undoRedo.source","timestamp":1732296995679},{"id":"nO6p.py","source":"undoRedo.source","timestamp":1732297308606},{"id":"a2Lr.py","timestamp":1732297739873},{"id":"7O28.py","timestamp":1736427587626},{"id":"mnSP.py","timestamp":1736427633920},{"id":"e6qt.py","timestamp":1736431114949},{"id":"MdFE.py","timestamp":1736431229706},{"id":"Oynq.py","timestamp":1736431290707},{"id":"ogMf.py","timestamp":1736431844132},{"id":"9I5k.py","timestamp":1736431908497},{"id":"Ksl3.py","timestamp":1736432435262},{"id":"zsQb.py","timestamp":1736432897631},{"id":"VrDU.py","timestamp":1736433234925},{"id":"1qIg.py","timestamp":1736433261315},{"id":"wkwf.py","timestamp":1736433344331},{"id":"6hZT.py","timestamp":1736433671585},{"id":"PIx2.py","timestamp":1736434089953},{"id":"0jvk.py","source":"undoRedo.source","timestamp":1736434275708},{"id":"13Ki.py","timestamp":1736434687552},{"id":"d0ve.py","timestamp":1736434861364},{"id":"q7LQ.py","timestamp":1736435037529},{"id":"uieM.py","timestamp":1736435156218},{"id":"58Ev.py","timestamp":1736437874510},{"id":"wr5N.py","timestamp":1736438155142},{"id":"I8Wi.py","timestamp":1736438354858},{"id":"H2jL.py","timestamp":1736445601426}]}